ai-talks/__init__.py
ai-talks/chat.py
ai-talks/src/__init__.py
ai-talks/src/styles/__init__.py
ai-talks/src/styles/menu_styles.py
ai-talks/src/utils/__init__.py
ai-talks/src/utils/conversation.py
ai-talks/src/utils/footer.py
ai-talks/src/utils/helpers.py
ai-talks/src/utils/lang.py
ai-talks/src/utils/stt.py
ai-talks/src/utils/tts.py
ai_talks/__init__.py
ai_talks/chat.py
ai_talks/src/__init__.py
ai_talks/src/styles/__init__.py
ai_talks/src/styles/menu_styles.py
ai_talks/src/utils/__init__.py
ai_talks/src/utils/conversation.py
ai_talks/src/utils/footer.py
ai_talks/src/utils/helpers.py
ai_talks/src/utils/lang.py
ai_talks/src/utils/stt.py
ai_talks/src/utils/tts.py
tests/__init__.py
tests/test_helpers.py
ai_talks-0.8.997.dist-info/LICENSE
ai_talks-0.8.997.dist-info/METADATA
ai_talks-0.8.997.dist-info/WHEEL
ai_talks-0.8.997.dist-info/entry_points.txt
ai_talks-0.8.997.dist-info/top_level.txt
ai_talks-0.8.997.dist-info/RECORD
