Metadata-Version: 2.1
Name: ai-talks
Version: 0.8.997
Summary: A ChatGPT API wrapper, providing a user-friendly Streamlit web interface
Home-page: https://github.com/dKosarevsky/AI-Talks
Author: Dmitry Kosarevsky
Author-email: if.kosarevsky@gmail.com
Classifier: Development Status :: 3 - Alpha
Classifier: License :: OSI Approved :: MIT License
Classifier: Programming Language :: Python :: 3
Classifier: Programming Language :: Python :: 3.10
Classifier: Programming Language :: Python :: 3.11
Classifier: Programming Language :: Python :: 3.12
License-File: LICENSE
Requires-Dist: pip (>=23.1)
Requires-Dist: streamlit (>=1.21.0)
Requires-Dist: streamlit-chat (>=0.0.2.2)
Requires-Dist: streamlit-option-menu (>=0.3.2)
Requires-Dist: openai (>=0.27.4)
Requires-Dist: gtts (>=2.3.1)
Requires-Dist: bokeh (==2.4.2)
Requires-Dist: streamlit-bokeh-events (>=0.1.2)
Requires-Dist: watchdog (>=3.0.0)
